twoToOneMux.v
module twoToOneMux(D0, D1, S, Y);

    input D0,D1,S;
    output Y;
    wire Y;
    
    assign Y = (S) ? D1 : D0;

endmodule;

twoToOneMux_tb.v
`timescale 1ns / 1ns
`include "twoToOneMux.v"

module twoToOneMux_tb;

reg D0;
reg D1;
reg S;
wire Y;

twoToOneMux UTT(D0,D1,S,Y);

initial begin
    $dumpfile("twoToOneMux_tb.vcd");
    $dumpvars(0, twoToOneMux_tb);

    // S | D0 | D1 || Y
    // 0 | 0 | 0 || 0
    $display("S | D0 | D1 || Y");

    S = 0;
    D0 = 0;
    D1 = 0;
    #20;
    $display("0 | 0 | 0 || %b", Y);

    // 0 | 0 | 1 || 0
    S = 0;
    D0 = 0;
    D1 = 1;
    #20;
    $display("0 | 0 | 1 || %b", Y);

    // 0 | 1 | 0 || 1
    S = 0;
    D0 = 1;
    D1 = 0;
    #20;
    $display("0 | 1 | 0 || %b", Y);

    // 0 | 1 | 1 || 1
    S = 0;
    D0 = 1;
    D1 = 1;
    #20;
    $display("0 | 1 | 1 || %b", Y);

    // 1 | 0 | 0 || 0
    S = 1;
    D0 = 0;
    D1 = 0;
    #20;
    $display("1 | 0 | 0 || %b", Y);

    // 1 | 0 | 1 || 1
    S = 1;
    D0 = 0;
    D1 = 1;
    #20;
    $display("1 | 0 | 1 || %b", Y);

    // 1 | 1 | 0 || 0
    S = 1;
    D0 = 1;
    D1 = 0;
    #20;
    $display("1 | 1 | 0 || %b", Y);

    // 1 | 1 | 1 || 1
    S = 1;
    D0 = 1;
    D1 = 1;
    #20;
    $display("1 | 1 | 1 || %b", Y);


    $display("Test Complete");

end

endmodule

twoToOneMux_tb.vcd
$date
	Wed Mar 09 16:28:34 2022
$end
$version
	Icarus Verilog
$end
$timescale
	1ns
$end
$scope module twoToOneMux_tb $end
$var wire 1 ! Y $end
$var reg 1 " D0 $end
$var reg 1 # D1 $end
$var reg 1 $ S $end
$scope module UTT $end
$var wire 1 " D0 $end
$var wire 1 # D1 $end
$var wire 1 $ S $end
$var wire 1 ! Y $end
$upscope $end
$upscope $end
$enddefinitions $end
#0
$dumpvars
0$
0#
0"
0!
$end
#20
1#
#40
1!
0#
1"
#60
1#
#80
0!
0#
0"
1$
#100
1!
1#
#120
0!
0#
1"
#140
1!
1#
